DESCRIPTION.rst
LICENSE.txt
README.rst
setup.py
optproblems/__init__.py
optproblems/base.py
optproblems/binary.py
optproblems/cec2007.py
optproblems/dtlz.py
optproblems/mpm.py
optproblems/multiobjective.py
optproblems/real.py
optproblems/wfg.py
optproblems/zdt.py
optproblems.egg-info/PKG-INFO
optproblems.egg-info/SOURCES.txt
optproblems.egg-info/dependency_links.txt
optproblems.egg-info/top_level.txt
optproblems/cec2005/__init__.py
optproblems/cec2005/basic_multimodal.py
optproblems/cec2005/expanded_multimodal.py
optproblems/cec2005/f15.py
optproblems/cec2005/f16.py
optproblems/cec2005/f17.py
optproblems/cec2005/f18.py
optproblems/cec2005/f19.py
optproblems/cec2005/f20.py
optproblems/cec2005/f21.py
optproblems/cec2005/f22.py
optproblems/cec2005/f23.py
optproblems/cec2005/f24.py
optproblems/cec2005/f25.py
optproblems/cec2005/helper.py
optproblems/cec2005/unimodal.py