Metadata-Version: 1.1
Name: optproblems
Version: 0.7
Summary: Infrastructure to define optimization problems and some test problems for black-box optimization
Home-page: https://ls11-www.cs.tu-dortmund.de/people/swessing/optproblems/doc/
Author: Simon Wessing
Author-email: simon.wessing@tu-dortmund.de
License: BSD
Keywords: objective function black-box optimization benchmark problem binary Dixon ZDT DTLZ WFG CEC
Platform: UNKNOWN
Classifier: Development Status :: 4 - Beta
Classifier: Intended Audience :: Science/Research
Classifier: Topic :: Scientific/Engineering
Classifier: Topic :: Scientific/Engineering :: Mathematics
Classifier: Topic :: Scientific/Engineering :: Artificial Intelligence
Classifier: License :: OSI Approved :: BSD License
Classifier: Programming Language :: Python :: 2
Classifier: Programming Language :: Python :: 2.7
Classifier: Programming Language :: Python :: 3
Classifier: Programming Language :: Python :: 3.4
